{
    "run_id": "bpE4GGhd",
    "meta": {
        "model": "deepLOB_TF",
        "modelKwargs": {
            "shape": [
                100,
                20,
                1
            ]
        },
        "numEpoch": 1,
        "ticker": "AMZN",
        "steps": [
            "TRAIN",
            "TEST"
        ],
        "trainTestSplit": 0.8,
        "maxFiles": 4,
        "threshold": "auto",
        "rowLim": 1000000,
        "lookForwardHorizon": 5,
        "representation": "orderflows",
        "startDate": "auto",
        "trainDays": 5,
        "batchSize": 64,
        "scaling": true
    },
    "accuracy": 0.5571150183677673
}